{
    "jap": {
        "no_epi": "12",
        "link": "https://player.ryuk.to?id=sugar-apple-fairy-tale-part-2-episode-",
        "down_links": [
            "MjA3Nzgy",
            "MjA4MTc4",
            "MjA4NTQ0",
            "MjA5MDQ5",
            "MjA5NTUw",
            "MjA5OTAy",
            "MjEwMjY5",
            "MjEwNzU1"
        ]
    },
    "eng": {
        "no_epi": "11",
        "link": "https://player.ryuk.to?id=sugar-apple-fairy-tale-part-2-dub-episode-",
        "down_links": [
            "MjA5MDY1",
            "MjA5MDY2",
            "MjA5NTcx",
            "MjA5OTEy",
            "MjEwMjgz",
            "MjEwNzYz"
        ]
    },
    "episodes_names": [
        "Sugar Apple Fairy Tale, Part 2",
        "Sugar Apple Fairy Tale, Part 2"
    ]
}