{
    "jap": {
        "no_epi": "32",
        "link": "https://player.ryuk.to?id=shounen-ashibe-go-go-goma-chan-3-episode-",
        "down_links": [
            "MTA0NzUz",
            "MTA0OTA1",
            "MTA1MDY0",
            "MTA1MTY3",
            "MTA1NDYy",
            "MTA1NTcw",
            "MTA1Njg1",
            "MTA1OTE1",
            "MTA2MDc4",
            "MTA2MTk0",
            "MTA2Mjkz",
            "MTA2NDA5",
            "MTA2NTEz",
            "MTA5OTUy",
            "MTEwMDQy",
            "MTEwMTc0",
            "MTEwMzg0",
            "MTEwNTA3",
            "MTEwNjIz",
            "MTEwODgz",
            "MTExMDAy",
            "MTExMTMx",
            "MTExMjMz",
            "MTExNDMz",
            "MTExNTcx",
            "MTExNzI5",
            "MTEyMzUy",
            "MTEyNTQx",
            "MTEyOTg3",
            "MTEzMjQw",
            "MTEzODE1",
            "MTE0MTAx"
        ]
    },
    "eng": {
        "no_epi": 0,
        "link": "https://player.ryuk.to?id=shounen-ashibe-go-go-goma-chan-3-dub-episode-",
        "down_links": []
    },
    "episodes_names": []
}