{
    "jap": {
        "no_epi": "52",
        "link": "https://player.ryuk.to?id=cardfight-vanguard-g-next-episode-",
        "down_links": [
            "NzY5NjE",
            "Nzc2Mzc",
            "Nzc2NDA",
            "NzgzNDI",
            "NzkyMjU",
            "ODA3ODA",
            "ODI4ODA",
            "ODY0ODA",
            "ODY0OTA",
            "ODc3MjU",
            "ODg2MTU",
            "OTA4OTI",
            "OTE0Mjk",
            "OTM1NTQ",
            "OTQ4MjI",
            "OTUzNzc",
            "OTU0Nzk",
            "OTU2NDI",
            "OTYwNDE",
            "OTY0OTI",
            "OTY2NDM",
            "OTY4Nzc",
            "OTcxMzg",
            "OTczMDQ",
            "OTc0ODI",
            "OTc1OTM",
            "OTc2ODY",
            "OTc3ODM",
            "OTc4NzI",
            "OTc5NzA",
            "OTgwNjc",
            "OTgxNTk",
            "OTgyNzY",
            "OTg0MzY",
            "OTg1MjQ",
            "OTg2MTE",
            "OTg4Mjk",
            "OTkwNDk",
            "OTkxNzk",
            "OTkzNzU",
            "OTk0ODg",
            "OTk2MDE",
            "OTk3Nzg",
            "MTAwMDQ5",
            "MTAwMTgz",
            "MTAwNDcz",
            "MTAwNjEw",
            "MTAwNzIy",
            "MTAwODM0",
            "MTAwOTc0",
            "MTAxMDg3",
            "MTAxMjA0"
        ]
    },
    "eng": {
        "no_epi": 0,
        "link": "https://player.ryuk.to?id=cardfight-vanguard-g-next-dub-episode-",
        "down_links": []
    },
    "episodes_names": [
        "01 "
    ]
}