{
    "jap": {
        "no_epi": "12",
        "link": "https://player.ryuk.to?id=princess-lover-episode-",
        "down_links": [
            "MzUyMTM=",
            "MzUyMTQ=",
            "MzUyMTU=",
            "MzUyMjM=",
            "MzUyMjg=",
            "MzUyMjk=",
            "MzUyMzA=",
            "MzUyMzE=",
            "MzUyMzI=",
            "MzUyMzM=",
            "MzUyMzQ=",
            "MzUyMzU="
        ]
    },
    "episodes_names": [
        "Noble Girl and a Horse Carriage",
        "Academy and Reunion",
        "Sword and Dance",
        "Rose and Shoe",
        "Sunset and Ferris Wheel",
        "Steam, Crying, and the Lucky Pervert",
        "Fiancee and Flower Petals",
        "Paradise and Reality",
        "Red and Blue",
        "Loss and Rebirth",
        "Cavalry and Train",
        "Princess Lover!"
    ],
    "fillers": []
}