{
    "jap": {
        "no_epi": "12",
        "link": "https://player.ryuk.to?id=yami-shibai-11-episode-",
        "down_links": [
            "MjA3ODc3",
            "MjA4MzEy",
            "MjA4Njkz",
            "MjA5MjA3",
            "MjA5NjUw",
            "MjEwMDAx",
            "MjEwNDU0"
        ]
    },
    "eng": {
        "no_epi": 0,
        "link": "https://player.ryuk.to?id=yami-shibai-11-dub-episode-",
        "down_links": []
    },
    "episodes_names": [
        "Yami Shibai 11"
    ]
}