{
    "jap": {
        "no_epi": "12",
        "link": "https://player.ryuk.to?id=king-of-prism-shiny-seven-stars-episode-",
        "down_links": [
            "MTE3NTQ3",
            "MTE4MzYy",
            "MTE4OTIz",
            "MTE5MzYz",
            "MTE5ODgw",
            "MTIwNTY3",
            "MTIxMTY0",
            "MTIxODA0",
            "MTIyMzAz",
            "MTIyNzM1",
            "MTIzMjI0",
            "MTIzODEx"
        ]
    },
    "episodes_names": [
        "Hayami Hiro, Mihama Koji, Nishina Kazuki: Beyond The Rainbow",
        "Tachibana Yukinojo Has Arrived!",
        "Kogami Taiga: The Festival! Is Inside Me!",
        "Juoin Kakeru: Soaring with Love",
        "The Shuffle: Joji's Song",
        "Takahashi Minato: My Heart Is an Ocean",
        "Saionji Leo: Flowers Blooming in Your \u2665",
        "Suzuno Yu: I Am Zeus",
        "Yamato Alexander: The Charisma of Street",
        "Kisaragi Louis: Prism Emissary",
        "Ichijo Shin: SIN",
        "Shiny Seven Stars Forever!"
    ],
    "fillers": []
}