{
    "jap": {
        "no_epi": "12",
        "link": "https://player.ryuk.to?id=senran-kagura--episode-",
        "down_links": [
            "MzczOTM=",
            "MzczOTQ=",
            "MzczOTU=",
            "MzczOTY=",
            "Mzc0MDQ=",
            "MzczOTc=",
            "Mzc0MDM=",
            "MzczOTg=",
            "Mzc0MDI=",
            "MzczOTk=",
            "Mzc0MDA=",
            "Mzc0MDE="
        ]
    },
    "episodes_names": [
        "Ninja That Stand Atop Skyscrapers",
        "The Legendary Shinobi Appears",
        "Moonlight Intruder",
        "Seaside Training - Shinobi Island",
        "Sneak Attack! Hanzo Academy",
        "Interlocking Shinobi Kekkai Barriers",
        "Hiking Terror",
        "A Shinobi Classroom Retrospective",
        "Hebijo Clandestine Girls' Academy",
        "Yin and Yang",
        "Castle Showdown",
        "Super-Secret Ninja Art"
    ],
    "fillers": []
}