{
    "jap": {
        "no_epi": "20",
        "link": "https://player.ryuk.to?id=mahou-shoujo-tai-arusu-episode-",
        "down_links": [
            "MTc0NTg5",
            "MTc0NTkw",
            "MTc0NTkx",
            "MTc0NTky",
            "MTc0NTkz",
            "MTc0NTk0",
            "MTc0NTk1",
            "MTc0NTk2",
            "MTc0NTk3",
            "MTc0NTk4",
            "MTc0NTk5",
            "MTc0NjAw",
            "MTc0NjAx",
            "MTc0NjAy",
            "MTc0NjAz",
            "MTc0NjA0",
            "MTc0NjA1",
            "MTc0NjA2",
            "MTc0NjA3",
            "MTc0NjA4"
        ]
    },
    "episodes_names": [
        "Episode 1",
        "Episode 2",
        "Episode 3",
        "Episode 4",
        "Episode 5",
        "Episode 6",
        "Episode 7",
        "Episode 8",
        "Episode 9",
        "Episode 10",
        "Episode 11",
        "Episode 12",
        "Episode 13",
        "Episode 14",
        "Episode 15",
        "Episode 16",
        "Episode 17",
        "Episode 18",
        "Episode 19",
        "Episode 20"
    ],
    "fillers": []
}