{
    "jap": {
        "no_epi": "13",
        "link": "https://player.ryuk.to?id=gunslinger-girl-episode-",
        "down_links": [
            "MjI1MTc=",
            "MjI1MTg=",
            "MjI1MTk=",
            "MjI1MjE=",
            "MjI1MjI=",
            "MjI1MjM=",
            "MjI1MjU=",
            "MjI1MjY=",
            "MjI1Mjk=",
            "MjI1MzA=",
            "MjI1MzI=",
            "MjI1MzM=",
            "MjI1MzU="
        ]
    },
    "eng": {
        "no_epi": "13",
        "link": "https://player.ryuk.to?id=gunslinger-girl-dub-episode-",
        "down_links": [
            "ODM1MjU=",
            "ODM1MjY=",
            "ODM1Mjc=",
            "ODM1Mjg=",
            "ODM1Mjk=",
            "ODM1MzA=",
            "ODM1MzE=",
            "ODM1MzI=",
            "ODM1MzM=",
            "ODM1MzQ=",
            "ODM1MzU=",
            "ODM1MzY=",
            "ODM1Mzc="
        ]
    },
    "episodes_names": [
        "Fratello (Siblings)",
        "Orione (Orion)",
        "Ragazzo (Boy)",
        "Bambola (Doll)",
        "Promessa (Promise)",
        "Gelato (Frozen)",
        "Protezione (Protection)",
        "Il Principe del regno della pasta (The Prince of the Kingdom of Pasta)",
        "Lycorsi Radiata Herb (Be Struck Off Herb)",
        "Amare (To Love)",
        "Febbre Alta (High Fever)",
        "Simbiosi (Symbiosis)",
        "Stellacadente (Falling Star)"
    ],
    "fillers": []
}