{
    "jap": {
        "no_epi": "4",
        "link": "https://player.ryuk.to?id=hikyou-tanken-fam-ihrlie-episode-",
        "down_links": [
            "MTQyMjMx",
            "MTQyMjMy",
            "MTQyMjMz",
            "MTQyMjM0"
        ]
    },
    "eng": {
        "no_epi": "4",
        "link": "https://player.ryuk.to?id=hikyou-tanken-fam-ihrlie-dub-episode-",
        "down_links": [
            "MTQyMjM1",
            "MTQyMjM2",
            "MTQyMjM3",
            "MTQyMjM4"
        ]
    },
    "episodes_names": [
        "As I Command Thee",
        "Oh, Spirits that Reside in the Air!",
        "Let the Light of Admonishment Shine Upon the Fools",
        "The Skies, the Seas, and the Woods"
    ],
    "fillers": []
}