{
    "jap": {
        "no_epi": "13",
        "link": "https://player.ryuk.to?id=hakozume-kouban-joshi-no-gyakushuu-episode-",
        "down_links": [
            "MTc3NzIw",
            "MTc3OTcw",
            "MTc4NTQ1",
            "MTc5Mjkw",
            "MTc5NzI1",
            "MTgwMjcz",
            "MTgwNzA4",
            "MTgxMjE0",
            "MTgxNzkz",
            "MTgyMjA5",
            "MTgyNjkw",
            "MTgzMDI3",
            "MTgzMzky"
        ]
    },
    "episodes_names": [
        "Unboxing & Punching Bag",
        "Beginner's Luck / Police Jungle",
        "The Ace Appears / The Body Speaks",
        "Dear Dog / Runner's High",
        "Late-Night Patrol / VS. a Molester",
        "Mixer Madness / Reckless Police",
        "Tailing Championship / Smooth Talker",
        "Rampage of Justice / Musclehead",
        "Arrest Technique / UFO",
        "Trauma",
        "Cannabis and Likeness/Sketch Artist Rhapsody",
        "Reenactment Doll / First Investigation Division",
        "Victory is Decided in an Instant"
    ],
    "fillers": []
}