{
    "1": {
        "intro": null,
        "title": "Episode 1",
        "source": {
            "DUBBED": {
                "Vid Streaming": {
                    "link": "https://www010.vipanicdn.net/streamhls/968970cf6ed021390570a7a4dc5c2abb/ep.1.1677680537.m3u8"
                },
                "Awesome Stream": {
                    "link": "https://player.ryuk.to?id=beyblade-burst-god-episode-dub-1"
                }
            },
            "SUBBED": {
                "Vid Streaming": {
                    "link": "https://www022.vipanicdn.net/streamhls/74faf577636cf9b32fe7cce761e6c9c5/ep.1.1677630692.m3u8"
                },
                "Awesome Stream": {
                    "link": "https://player.ryuk.to?id=beyblade-burst-god-episode-1"
                }
            },
            "OTHER LANGUAGES": {
                "Hindi": "https://beta.awstream.net/watch?v=beyblade-burst-evolution-8211-episode-01&lang=hin"
            }
        },
        "isFiller": false,
        "downloadLink": {
            "DUBBED": "MTEzNTI5",
            "SUBBED": "OTc2MTE="
        }
    },
    "2": {
        "intro": null,
        "title": "Episode 2",
        "source": {
            "DUBBED": {
                "Vid Streaming": {
                    "link": "https://www011.vipanicdn.net/streamhls/968970cf6ed021390570a7a4dc5c2abb/ep.2.1677697644.m3u8"
                },
                "Awesome Stream": {
                    "link": "https://player.ryuk.to?id=beyblade-burst-god-episode-dub-2"
                }
            },
            "SUBBED": {
                "Vid Streaming": {
                    "link": "https://www028.vipanicdn.net/streamhls/74faf577636cf9b32fe7cce761e6c9c5/ep.2.1677681306.m3u8"
                },
                "Awesome Stream": {
                    "link": "https://player.ryuk.to?id=beyblade-burst-god-episode-2"
                }
            },
            "OTHER LANGUAGES": {
                "Hindi": "https://beta.awstream.net/watch?v=beyblade-burst-evolution-8211-episode-02&lang=hin"
            }
        },
        "isFiller": false,
        "downloadLink": {
            "DUBBED": "MTEzNTMw",
            "SUBBED": "OTc3MDc="
        }
    },
    "3": {
        "intro": null,
        "title": "Episode 3",
        "source": {
            "DUBBED": {
                "Vid Streaming": {
                    "link": "https://www012.vipanicdn.net/streamhls/968970cf6ed021390570a7a4dc5c2abb/ep.3.1677678124.m3u8"
                },
                "Awesome Stream": {
                    "link": "https://player.ryuk.to?id=beyblade-burst-god-episode-dub-3"
                }
            },
            "SUBBED": {
                "Vid Streaming": {
                    "link": "https://www008.vipanicdn.net/streamhls/74faf577636cf9b32fe7cce761e6c9c5/ep.3.1677678172.m3u8"
                },
                "Awesome Stream": {
                    "link": "https://player.ryuk.to?id=beyblade-burst-god-episode-3"
                }
            },
            "OTHER LANGUAGES": {
                "Hindi": "https://beta.awstream.net/watch?v=beyblade-burst-evolution-8211-episode-03&lang=hin"
            }
        },
        "isFiller": false,
        "downloadLink": {
            "DUBBED": "MTEzNTMx",
            "SUBBED": "OTc4MDc="
        }
    },
    "4": {
        "intro": null,
        "title": "Episode 4",
        "source": {
            "DUBBED": {
                "Vid Streaming": {
                    "link": "https://www013.vipanicdn.net/streamhls/968970cf6ed021390570a7a4dc5c2abb/ep.4.1677685078.m3u8"
                },
                "Awesome Stream": {
                    "link": "https://player.ryuk.to?id=beyblade-burst-god-episode-dub-4"
                }
            },
            "SUBBED": {
                "Vid Streaming": {
                    "link": "https://www009.vipanicdn.net/streamhls/74faf577636cf9b32fe7cce761e6c9c5/ep.4.1677679946.m3u8"
                },
                "Awesome Stream": {
                    "link": "https://player.ryuk.to?id=beyblade-burst-god-episode-4"
                }
            },
            "OTHER LANGUAGES": {
                "Hindi": "https://beta.awstream.net/watch?v=beyblade-burst-evolution-8211-episode-04&lang=hin"
            }
        },
        "isFiller": false,
        "downloadLink": {
            "DUBBED": "MTEzNTMy",
            "SUBBED": "MTAwNDc4"
        }
    },
    "5": {
        "intro": null,
        "title": "Episode 5",
        "source": {
            "DUBBED": {
                "Vid Streaming": {
                    "link": "https://www014.vipanicdn.net/streamhls/968970cf6ed021390570a7a4dc5c2abb/ep.5.1677676732.m3u8"
                },
                "Awesome Stream": {
                    "link": "https://player.ryuk.to?id=beyblade-burst-god-episode-dub-5"
                }
            },
            "SUBBED": {
                "Vid Streaming": {
                    "link": "https://www019.vipanicdn.net/streamhls/74faf577636cf9b32fe7cce761e6c9c5/ep.5.1677681265.m3u8"
                },
                "Awesome Stream": {
                    "link": "https://player.ryuk.to?id=beyblade-burst-god-episode-5"
                }
            },
            "OTHER LANGUAGES": {
                "Hindi": "https://beta.awstream.net/watch?v=beyblade-burst-evolution-8211-episode-05&lang=hin"
            }
        },
        "isFiller": false,
        "downloadLink": {
            "DUBBED": "MTEzNTMz",
            "SUBBED": "MTAyNDY4"
        }
    },
    "6": {
        "intro": null,
        "title": "Episode 6",
        "source": {
            "DUBBED": {
                "Vid Streaming": {
                    "link": "https://www015.vipanicdn.net/streamhls/968970cf6ed021390570a7a4dc5c2abb/ep.6.1677681075.m3u8"
                },
                "Awesome Stream": {
                    "link": "https://player.ryuk.to?id=beyblade-burst-god-episode-dub-6"
                }
            },
            "SUBBED": {
                "Vid Streaming": {
                    "link": "https://www020.vipanicdn.net/streamhls/74faf577636cf9b32fe7cce761e6c9c5/ep.6.1677681465.m3u8"
                },
                "Awesome Stream": {
                    "link": "https://player.ryuk.to?id=beyblade-burst-god-episode-6"
                }
            },
            "OTHER LANGUAGES": {
                "Hindi": "https://beta.awstream.net/watch?v=beyblade-burst-evolution-8211-episode-06&lang=hin"
            }
        },
        "isFiller": false,
        "downloadLink": {
            "DUBBED": "MTEzNTM0",
            "SUBBED": "MTAyNDY5"
        }
    },
    "7": {
        "intro": null,
        "title": "Episode 7",
        "source": {
            "DUBBED": {
                "Vid Streaming": {
                    "link": "https://www016.vipanicdn.net/streamhls/968970cf6ed021390570a7a4dc5c2abb/ep.7.1677686903.m3u8"
                },
                "Awesome Stream": {
                    "link": "https://player.ryuk.to?id=beyblade-burst-god-episode-dub-7"
                }
            },
            "SUBBED": {
                "Vid Streaming": {
                    "link": "https://www021.vipanicdn.net/streamhls/74faf577636cf9b32fe7cce761e6c9c5/ep.7.1677680863.m3u8"
                },
                "Awesome Stream": {
                    "link": "https://player.ryuk.to?id=beyblade-burst-god-episode-7"
                }
            },
            "OTHER LANGUAGES": {
                "Hindi": "https://beta.awstream.net/watch?v=beyblade-burst-evolution-8211-episode-07&lang=hin"
            }
        },
        "isFiller": false,
        "downloadLink": {
            "DUBBED": "MTEzNTM1",
            "SUBBED": "MTAyNDcw"
        }
    },
    "8": {
        "intro": null,
        "title": "Episode 8",
        "source": {
            "DUBBED": {
                "Vid Streaming": {
                    "link": "https://www017.vipanicdn.net/streamhls/968970cf6ed021390570a7a4dc5c2abb/ep.8.1677690058.m3u8"
                },
                "Awesome Stream": {
                    "link": "https://player.ryuk.to?id=beyblade-burst-god-episode-dub-8"
                }
            },
            "SUBBED": {
                "Vid Streaming": {
                    "link": "https://www022.vipanicdn.net/streamhls/74faf577636cf9b32fe7cce761e6c9c5/ep.8.1677677855.m3u8"
                },
                "Awesome Stream": {
                    "link": "https://player.ryuk.to?id=beyblade-burst-god-episode-8"
                }
            },
            "OTHER LANGUAGES": {
                "Hindi": "https://beta.awstream.net/watch?v=beyblade-burst-evolution-8211-episode-08&lang=hin"
            }
        },
        "isFiller": false,
        "downloadLink": {
            "DUBBED": "MTEzNTM2",
            "SUBBED": "MTAyNDcx"
        }
    },
    "9": {
        "intro": null,
        "title": "Episode 9",
        "source": {
            "DUBBED": {
                "Vid Streaming": {
                    "link": "https://www018.vipanicdn.net/streamhls/968970cf6ed021390570a7a4dc5c2abb/ep.9.1677684539.m3u8"
                },
                "Awesome Stream": {
                    "link": "https://player.ryuk.to?id=beyblade-burst-god-episode-dub-9"
                }
            },
            "SUBBED": {
                "Vid Streaming": {
                    "link": "https://www023.vipanicdn.net/streamhls/74faf577636cf9b32fe7cce761e6c9c5/ep.9.1677738809.m3u8"
                },
                "Awesome Stream": {
                    "link": "https://player.ryuk.to?id=beyblade-burst-god-episode-9"
                }
            },
            "OTHER LANGUAGES": {
                "Hindi": "https://beta.awstream.net/watch?v=beyblade-burst-evolution-8211-episode-09&lang=hin"
            }
        },
        "isFiller": false,
        "downloadLink": {
            "DUBBED": "MTEzNTM3",
            "SUBBED": "MTAyNDcy"
        }
    },
    "10": {
        "intro": null,
        "title": "Episode 10",
        "source": {
            "DUBBED": {
                "Vid Streaming": {
                    "link": "https://www019.vipanicdn.net/streamhls/968970cf6ed021390570a7a4dc5c2abb/ep.10.1677687719.m3u8"
                },
                "Awesome Stream": {
                    "link": "https://player.ryuk.to?id=beyblade-burst-god-episode-dub-10"
                }
            },
            "SUBBED": {
                "Vid Streaming": {
                    "link": "https://www024.vipanicdn.net/streamhls/74faf577636cf9b32fe7cce761e6c9c5/ep.10.1677685422.m3u8"
                },
                "Awesome Stream": {
                    "link": "https://player.ryuk.to?id=beyblade-burst-god-episode-10"
                }
            },
            "OTHER LANGUAGES": {
                "Hindi": "https://beta.awstream.net/watch?v=beyblade-burst-evolution-8211-episode-10&lang=hin"
            }
        },
        "isFiller": false,
        "downloadLink": {
            "DUBBED": "MTEzNTM4",
            "SUBBED": "MTAyNDcz"
        }
    },
    "11": {
        "intro": null,
        "title": "Episode 11",
        "source": {
            "DUBBED": {
                "Vid Streaming": {
                    "link": "https://www020.vipanicdn.net/streamhls/968970cf6ed021390570a7a4dc5c2abb/ep.11.1677688358.m3u8"
                },
                "Awesome Stream": {
                    "link": "https://player.ryuk.to?id=beyblade-burst-god-episode-dub-11"
                }
            },
            "SUBBED": {
                "Vid Streaming": {
                    "link": "https://www025.vipanicdn.net/streamhls/74faf577636cf9b32fe7cce761e6c9c5/ep.11.1677750386.m3u8"
                },
                "Awesome Stream": {
                    "link": "https://player.ryuk.to?id=beyblade-burst-god-episode-11"
                }
            },
            "OTHER LANGUAGES": {
                "Hindi": "https://beta.awstream.net/watch?v=beyblade-burst-evolution-8211-episode-11&lang=hin"
            }
        },
        "isFiller": false,
        "downloadLink": {
            "DUBBED": "MTEzNTM5",
            "SUBBED": "MTAyNDc0"
        }
    },
    "12": {
        "intro": null,
        "title": "Episode 12",
        "source": {
            "DUBBED": {
                "Vid Streaming": {
                    "link": "https://www021.vipanicdn.net/streamhls/968970cf6ed021390570a7a4dc5c2abb/ep.12.1677687446.m3u8"
                },
                "Awesome Stream": {
                    "link": "https://player.ryuk.to?id=beyblade-burst-god-episode-dub-12"
                }
            },
            "SUBBED": {
                "Vid Streaming": {
                    "link": "https://www027.vipanicdn.net/streamhls/74faf577636cf9b32fe7cce761e6c9c5/ep.12.1677728758.m3u8"
                },
                "Awesome Stream": {
                    "link": "https://player.ryuk.to?id=beyblade-burst-god-episode-12"
                }
            },
            "OTHER LANGUAGES": {
                "Hindi": "https://beta.awstream.net/watch?v=beyblade-burst-evolution-8211-episode-12&lang=hin"
            }
        },
        "isFiller": false,
        "downloadLink": {
            "DUBBED": "MTEzNTQw",
            "SUBBED": "MTAyNDc2"
        }
    },
    "13": {
        "intro": null,
        "title": "Episode 13",
        "source": {
            "DUBBED": {
                "Vid Streaming": {
                    "link": "https://www022.vipanicdn.net/streamhls/968970cf6ed021390570a7a4dc5c2abb/ep.13.1677682457.m3u8"
                },
                "Awesome Stream": {
                    "link": "https://player.ryuk.to?id=beyblade-burst-god-episode-dub-13"
                }
            },
            "SUBBED": {
                "Vid Streaming": {
                    "link": "https://www028.vipanicdn.net/streamhls/74faf577636cf9b32fe7cce761e6c9c5/ep.13.1677683944.m3u8"
                },
                "Awesome Stream": {
                    "link": "https://player.ryuk.to?id=beyblade-burst-god-episode-13"
                }
            },
            "OTHER LANGUAGES": {
                "Hindi": "https://beta.awstream.net/watch?v=beyblade-burst-evolution-8211-episode-13&lang=hin"
            }
        },
        "isFiller": false,
        "downloadLink": {
            "DUBBED": "MTEzNTQx",
            "SUBBED": "MTAyNDc3"
        }
    },
    "14": {
        "intro": null,
        "title": "Episode 14",
        "source": {
            "DUBBED": {
                "Vid Streaming": {
                    "link": "https://www023.vipanicdn.net/streamhls/968970cf6ed021390570a7a4dc5c2abb/ep.14.1677754567.m3u8"
                },
                "Awesome Stream": {
                    "link": "https://player.ryuk.to?id=beyblade-burst-god-episode-dub-14"
                }
            },
            "SUBBED": {
                "Vid Streaming": {
                    "link": "https://www013.vipanicdn.net/streamhls/74faf577636cf9b32fe7cce761e6c9c5/ep.14.1677679446.m3u8"
                },
                "Awesome Stream": {
                    "link": "https://player.ryuk.to?id=beyblade-burst-god-episode-14"
                }
            },
            "OTHER LANGUAGES": {
                "Hindi": "https://beta.awstream.net/watch?v=beyblade-burst-evolution-8211-episode-14&lang=hin"
            }
        },
        "isFiller": false,
        "downloadLink": {
            "DUBBED": "MTEzNTQy",
            "SUBBED": "MTAzMTUy"
        }
    },
    "15": {
        "intro": null,
        "title": "Episode 15",
        "source": {
            "DUBBED": {
                "Vid Streaming": {
                    "link": "https://www024.vipanicdn.net/streamhls/968970cf6ed021390570a7a4dc5c2abb/ep.15.1677691982.m3u8"
                },
                "Awesome Stream": {
                    "link": "https://player.ryuk.to?id=beyblade-burst-god-episode-dub-15"
                }
            },
            "SUBBED": {
                "Vid Streaming": {
                    "link": "https://www014.vipanicdn.net/streamhls/74faf577636cf9b32fe7cce761e6c9c5/ep.15.1677673801.m3u8"
                },
                "Awesome Stream": {
                    "link": "https://player.ryuk.to?id=beyblade-burst-god-episode-15"
                }
            },
            "OTHER LANGUAGES": {
                "Hindi": "https://beta.awstream.net/watch?v=beyblade-burst-evolution-8211-episode-15&lang=hin"
            }
        },
        "isFiller": false,
        "downloadLink": {
            "DUBBED": "MTEzNTQz",
            "SUBBED": "MTAzMTUz"
        }
    },
    "16": {
        "intro": null,
        "title": "Episode 16",
        "source": {
            "DUBBED": {
                "Vid Streaming": {
                    "link": "https://www025.vipanicdn.net/streamhls/968970cf6ed021390570a7a4dc5c2abb/ep.16.1677774583.m3u8"
                },
                "Awesome Stream": {
                    "link": "https://player.ryuk.to?id=beyblade-burst-god-episode-dub-16"
                }
            },
            "SUBBED": {
                "Vid Streaming": {
                    "link": "https://www017.vipanicdn.net/streamhls/74faf577636cf9b32fe7cce761e6c9c5/ep.16.1677683784.m3u8"
                },
                "Awesome Stream": {
                    "link": "https://player.ryuk.to?id=beyblade-burst-god-episode-16"
                }
            },
            "OTHER LANGUAGES": {
                "Hindi": "https://beta.awstream.net/watch?v=beyblade-burst-evolution-8211-episode-16&lang=hin"
            }
        },
        "isFiller": false,
        "downloadLink": {
            "DUBBED": "MTEzNTQ0",
            "SUBBED": "MTAzNDI2"
        }
    },
    "17": {
        "intro": null,
        "title": "Episode 17",
        "source": {
            "DUBBED": {
                "Vid Streaming": {
                    "link": "https://www026.vipanicdn.net/streamhls/968970cf6ed021390570a7a4dc5c2abb/ep.17.1677693168.m3u8"
                },
                "Awesome Stream": {
                    "link": "https://player.ryuk.to?id=beyblade-burst-god-episode-dub-17"
                }
            },
            "SUBBED": {
                "Vid Streaming": {
                    "link": "https://www018.vipanicdn.net/streamhls/74faf577636cf9b32fe7cce761e6c9c5/ep.17.1677680802.m3u8"
                },
                "Awesome Stream": {
                    "link": "https://player.ryuk.to?id=beyblade-burst-god-episode-17"
                }
            },
            "OTHER LANGUAGES": {
                "Hindi": "https://beta.awstream.net/watch?v=beyblade-burst-evolution-8211-episode-17&lang=hin"
            }
        },
        "isFiller": false,
        "downloadLink": {
            "DUBBED": "MTEzNTQ1",
            "SUBBED": "MTAzNDI3"
        }
    },
    "18": {
        "intro": null,
        "title": "Episode 18",
        "source": {
            "DUBBED": {
                "Vid Streaming": {
                    "link": "https://www027.vipanicdn.net/streamhls/968970cf6ed021390570a7a4dc5c2abb/ep.18.1677747109.m3u8"
                },
                "Awesome Stream": {
                    "link": "https://player.ryuk.to?id=beyblade-burst-god-episode-dub-18"
                }
            },
            "SUBBED": {
                "Vid Streaming": {
                    "link": "https://www001.vipanicdn.net/streamhls/74faf577636cf9b32fe7cce761e6c9c5/ep.18.1677686021.m3u8"
                },
                "Awesome Stream": {
                    "link": "https://player.ryuk.to?id=beyblade-burst-god-episode-18"
                }
            },
            "OTHER LANGUAGES": {
                "Hindi": "https://beta.awstream.net/watch?v=beyblade-burst-evolution-8211-episode-18&lang=hin"
            }
        },
        "isFiller": false,
        "downloadLink": {
            "DUBBED": "MTEzNTQ2",
            "SUBBED": "MTA1OTYw"
        }
    },
    "19": {
        "intro": null,
        "title": "Episode 19",
        "source": {
            "DUBBED": {
                "Vid Streaming": {
                    "link": "https://www028.vipanicdn.net/streamhls/968970cf6ed021390570a7a4dc5c2abb/ep.19.1677690800.m3u8"
                },
                "Awesome Stream": {
                    "link": "https://player.ryuk.to?id=beyblade-burst-god-episode-dub-19"
                }
            },
            "SUBBED": {
                "Vid Streaming": {
                    "link": "https://www023.vipanicdn.net/streamhls/74faf577636cf9b32fe7cce761e6c9c5/ep.19.1677744681.m3u8"
                },
                "Awesome Stream": {
                    "link": "https://player.ryuk.to?id=beyblade-burst-god-episode-19"
                }
            },
            "OTHER LANGUAGES": {
                "Hindi": "https://beta.awstream.net/watch?v=beyblade-burst-evolution-8211-episode-19&lang=hin"
            }
        },
        "isFiller": false,
        "downloadLink": {
            "DUBBED": "MTEzNTQ3",
            "SUBBED": "MTA2MTAy"
        }
    },
    "20": {
        "intro": null,
        "title": "Episode 20",
        "source": {
            "DUBBED": {
                "Vid Streaming": {
                    "link": "https://www029.vipanicdn.net/streamhls/968970cf6ed021390570a7a4dc5c2abb/ep.20.1677689413.m3u8"
                },
                "Awesome Stream": {
                    "link": "https://player.ryuk.to?id=beyblade-burst-god-episode-dub-20"
                }
            },
            "SUBBED": {
                "Vid Streaming": {
                    "link": "https://www022.vipanicdn.net/streamhls/74faf577636cf9b32fe7cce761e6c9c5/ep.20.1677679923.m3u8"
                },
                "Awesome Stream": {
                    "link": "https://player.ryuk.to?id=beyblade-burst-god-episode-20"
                }
            },
            "OTHER LANGUAGES": {
                "Hindi": "https://beta.awstream.net/watch?v=beyblade-burst-evolution-8211-episode-20&lang=hin"
            }
        },
        "isFiller": false,
        "downloadLink": {
            "DUBBED": "MTEzNTQ4",
            "SUBBED": "MTA2MzEx"
        }
    },
    "21": {
        "intro": null,
        "title": "Episode 21",
        "source": {
            "DUBBED": {
                "Vid Streaming": {
                    "link": "https://www030.vipanicdn.net/streamhls/968970cf6ed021390570a7a4dc5c2abb/ep.21.1677686983.m3u8"
                },
                "Awesome Stream": {
                    "link": "https://player.ryuk.to?id=beyblade-burst-god-episode-dub-21"
                }
            },
            "SUBBED": {
                "Vid Streaming": {
                    "link": "https://www024.vipanicdn.net/streamhls/74faf577636cf9b32fe7cce761e6c9c5/ep.21.1677688026.m3u8"
                },
                "Awesome Stream": {
                    "link": "https://player.ryuk.to?id=beyblade-burst-god-episode-21"
                }
            },
            "OTHER LANGUAGES": {
                "Hindi": "https://beta.awstream.net/watch?v=beyblade-burst-evolution-8211-episode-21&lang=hin"
            }
        },
        "isFiller": false,
        "downloadLink": {
            "DUBBED": "MTEzNTQ5",
            "SUBBED": "MTA2MzEz"
        }
    },
    "22": {
        "intro": null,
        "title": "Episode 22",
        "source": {
            "DUBBED": {
                "Vid Streaming": {
                    "link": "https://www001.vipanicdn.net/streamhls/968970cf6ed021390570a7a4dc5c2abb/ep.22.1677690954.m3u8"
                },
                "Awesome Stream": {
                    "link": "https://player.ryuk.to?id=beyblade-burst-god-episode-dub-22"
                }
            },
            "SUBBED": {
                "Vid Streaming": {
                    "link": "https://www034.vipanicdn.net/streamhls/74faf577636cf9b32fe7cce761e6c9c5/ep.22.1677813759.m3u8"
                },
                "Awesome Stream": {
                    "link": "https://player.ryuk.to?id=beyblade-burst-god-episode-22"
                }
            },
            "OTHER LANGUAGES": {
                "Hindi": "https://beta.awstream.net/watch?v=beyblade-burst-evolution-8211-episode-22&lang=hin"
            }
        },
        "isFiller": false,
        "downloadLink": {
            "DUBBED": "MTEzNTUw",
            "SUBBED": "MTk4MzIz"
        }
    },
    "23": {
        "intro": null,
        "title": "Episode 23",
        "source": {
            "DUBBED": {
                "Vid Streaming": {
                    "link": "https://www002.vipanicdn.net/streamhls/968970cf6ed021390570a7a4dc5c2abb/ep.23.1677684600.m3u8"
                },
                "Awesome Stream": {
                    "link": "https://player.ryuk.to?id=beyblade-burst-god-episode-dub-23"
                }
            },
            "SUBBED": {
                "Vid Streaming": {
                    "link": "https://www049.vipanicdn.net/streamhls/74faf577636cf9b32fe7cce761e6c9c5/ep.23.1677834163.m3u8"
                },
                "Awesome Stream": {
                    "link": "https://player.ryuk.to?id=beyblade-burst-god-episode-23"
                }
            },
            "OTHER LANGUAGES": {
                "Hindi": "https://beta.awstream.net/watch?v=beyblade-burst-evolution-8211-episode-23&lang=hin"
            }
        },
        "isFiller": false,
        "downloadLink": {
            "DUBBED": "MTEzNTUx",
            "SUBBED": "MTk4NzE4"
        }
    },
    "24": {
        "intro": null,
        "title": "Episode 24",
        "source": {
            "DUBBED": {
                "Vid Streaming": {
                    "link": "https://www003.vipanicdn.net/streamhls/968970cf6ed021390570a7a4dc5c2abb/ep.24.1677683359.m3u8"
                },
                "Awesome Stream": {
                    "link": "https://player.ryuk.to?id=beyblade-burst-god-episode-dub-24"
                }
            },
            "SUBBED": {
                "Vid Streaming": {
                    "link": "https://www042.vipanicdn.net/streamhls/74faf577636cf9b32fe7cce761e6c9c5/ep.24.1677833569.m3u8"
                },
                "Awesome Stream": {
                    "link": "https://player.ryuk.to?id=beyblade-burst-god-episode-24"
                }
            },
            "OTHER LANGUAGES": {
                "Hindi": "https://beta.awstream.net/watch?v=beyblade-burst-evolution-8211-episode-24&lang=hin"
            }
        },
        "isFiller": false,
        "downloadLink": {
            "DUBBED": "MTEzNTUy",
            "SUBBED": "MTk5MDkx"
        }
    },
    "25": {
        "intro": null,
        "title": "Episode 25",
        "source": {
            "DUBBED": {
                "Vid Streaming": {
                    "link": "https://www004.vipanicdn.net/streamhls/968970cf6ed021390570a7a4dc5c2abb/ep.25.1677682420.m3u8"
                },
                "Awesome Stream": {
                    "link": "https://player.ryuk.to?id=beyblade-burst-god-episode-dub-25"
                }
            },
            "SUBBED": {
                "Vid Streaming": {
                    "link": "https://www044.vipanicdn.net/streamhls/74faf577636cf9b32fe7cce761e6c9c5/ep.25.1677837553.m3u8"
                },
                "Awesome Stream": {
                    "link": "https://player.ryuk.to?id=beyblade-burst-god-episode-25"
                }
            },
            "OTHER LANGUAGES": {
                "Hindi": "https://beta.awstream.net/watch?v=beyblade-burst-evolution-8211-episode-25&lang=hin"
            }
        },
        "isFiller": false,
        "downloadLink": {
            "DUBBED": "MTEzNTUz",
            "SUBBED": "MTk5Nzkz"
        }
    },
    "26": {
        "intro": null,
        "title": "Episode 26",
        "source": {
            "DUBBED": {
                "Vid Streaming": {
                    "link": "https://www005.vipanicdn.net/streamhls/968970cf6ed021390570a7a4dc5c2abb/ep.26.1677690911.m3u8"
                },
                "Awesome Stream": {
                    "link": "https://player.ryuk.to?id=beyblade-burst-god-episode-dub-26"
                }
            },
            "SUBBED": {
                "Vid Streaming": {
                    "link": "https://www046.vipanicdn.net/streamhls/74faf577636cf9b32fe7cce761e6c9c5/ep.26.1691461702.m3u8"
                },
                "Awesome Stream": {
                    "link": "https://player.ryuk.to?id=beyblade-burst-god-episode-26"
                }
            },
            "OTHER LANGUAGES": {
                "Hindi": "https://beta.awstream.net/watch?v=beyblade-burst-evolution-8211-episode-26&lang=hin"
            }
        },
        "isFiller": false,
        "downloadLink": {
            "DUBBED": "MTEzNTU0",
            "SUBBED": "MjAwNjc1"
        }
    },
    "27": {
        "intro": null,
        "title": "Episode 27",
        "source": {
            "DUBBED": {
                "Vid Streaming": {
                    "link": "https://www006.vipanicdn.net/streamhls/968970cf6ed021390570a7a4dc5c2abb/ep.27.1677685622.m3u8"
                },
                "Awesome Stream": {
                    "link": "https://player.ryuk.to?id=beyblade-burst-god-episode-dub-27"
                }
            },
            "SUBBED": {
                "Vid Streaming": {
                    "link": "https://www046.vipanicdn.net/streamhls/74faf577636cf9b32fe7cce761e6c9c5/ep.27.1679281468.m3u8"
                },
                "Awesome Stream": {
                    "link": "https://player.ryuk.to?id=beyblade-burst-god-episode-27"
                }
            },
            "OTHER LANGUAGES": {
                "Hindi": "https://beta.awstream.net/watch?v=beyblade-burst-evolution-8211-episode-27&lang=hin"
            }
        },
        "isFiller": false,
        "downloadLink": {
            "DUBBED": "MTEzNTU1",
            "SUBBED": "MjAxMzE1"
        }
    },
    "28": {
        "intro": null,
        "title": "Episode 28",
        "source": {
            "DUBBED": {
                "Vid Streaming": {
                    "link": "https://www007.vipanicdn.net/streamhls/968970cf6ed021390570a7a4dc5c2abb/ep.28.1677683381.m3u8"
                },
                "Awesome Stream": {
                    "link": "https://player.ryuk.to?id=beyblade-burst-god-episode-dub-28"
                }
            },
            "SUBBED": {
                "Vid Streaming": {
                    "link": "https://www041.vipanicdn.net/streamhls/74faf577636cf9b32fe7cce761e6c9c5/ep.28.1679724871.m3u8"
                },
                "Awesome Stream": {
                    "link": "https://player.ryuk.to?id=beyblade-burst-god-episode-28"
                }
            },
            "OTHER LANGUAGES": {
                "Hindi": "https://beta.awstream.net/watch?v=beyblade-burst-evolution-8211-episode-28&lang=hin"
            }
        },
        "isFiller": false,
        "downloadLink": {
            "DUBBED": "MTEzNTU2",
            "SUBBED": "MjAxNjEw"
        }
    },
    "29": {
        "intro": null,
        "title": "Episode 29",
        "source": {
            "DUBBED": {
                "Vid Streaming": {
                    "link": "https://www008.vipanicdn.net/streamhls/968970cf6ed021390570a7a4dc5c2abb/ep.29.1677684293.m3u8"
                },
                "Awesome Stream": {
                    "link": "https://player.ryuk.to?id=beyblade-burst-god-episode-dub-29"
                }
            },
            "SUBBED": {
                "Vid Streaming": {
                    "link": "https://www040.vipanicdn.net/streamhls/74faf577636cf9b32fe7cce761e6c9c5/ep.29.1680426020.m3u8"
                },
                "Awesome Stream": {
                    "link": "https://player.ryuk.to?id=beyblade-burst-god-episode-29"
                }
            },
            "OTHER LANGUAGES": {
                "Hindi": "https://beta.awstream.net/watch?v=beyblade-burst-evolution-8211-episode-29&lang=hin"
            }
        },
        "isFiller": false,
        "downloadLink": {
            "DUBBED": "MTEzNTU3",
            "SUBBED": "MjAyMDQ5"
        }
    },
    "30": {
        "intro": null,
        "title": "Episode 30",
        "source": {
            "DUBBED": {
                "Vid Streaming": {
                    "link": "https://www009.vipanicdn.net/streamhls/968970cf6ed021390570a7a4dc5c2abb/ep.30.1677685440.m3u8"
                },
                "Awesome Stream": {
                    "link": "https://player.ryuk.to?id=beyblade-burst-god-episode-dub-30"
                }
            },
            "SUBBED": {
                "Vid Streaming": {
                    "link": "https://www053.vipanicdn.net/streamhls/74faf577636cf9b32fe7cce761e6c9c5/ep.30.1683348049.m3u8"
                },
                "Awesome Stream": {
                    "link": "https://player.ryuk.to?id=beyblade-burst-god-episode-30"
                }
            },
            "OTHER LANGUAGES": {
                "Hindi": "https://beta.awstream.net/watch?v=beyblade-burst-evolution-8211-episode-30&lang=hin"
            }
        },
        "isFiller": false,
        "downloadLink": {
            "DUBBED": "MTEzNTU4",
            "SUBBED": "MjAzODYy"
        }
    },
    "31": {
        "intro": null,
        "title": "Episode 31",
        "source": {
            "DUBBED": {
                "Vid Streaming": {
                    "link": "https://www010.vipanicdn.net/streamhls/968970cf6ed021390570a7a4dc5c2abb/ep.31.1677680540.m3u8"
                },
                "Awesome Stream": {
                    "link": "https://player.ryuk.to?id=beyblade-burst-god-episode-dub-31"
                }
            },
            "SUBBED": {
                "Vid Streaming": {
                    "link": "https://www053.vipanicdn.net/streamhls/74faf577636cf9b32fe7cce761e6c9c5/ep.31.1683351372.m3u8"
                },
                "Awesome Stream": {
                    "link": "https://player.ryuk.to?id=beyblade-burst-god-episode-31"
                }
            },
            "OTHER LANGUAGES": {
                "Hindi": "https://beta.awstream.net/watch?v=beyblade-burst-evolution-8211-episode-31&lang=hin"
            }
        },
        "isFiller": false,
        "downloadLink": {
            "DUBBED": "MTEzNTU5",
            "SUBBED": "MjA0MDM3"
        }
    },
    "32": {
        "intro": null,
        "title": "Episode 32",
        "source": {
            "DUBBED": {
                "Vid Streaming": {
                    "link": "https://www011.vipanicdn.net/streamhls/968970cf6ed021390570a7a4dc5c2abb/ep.32.1677697656.m3u8"
                },
                "Awesome Stream": {
                    "link": "https://player.ryuk.to?id=beyblade-burst-god-episode-dub-32"
                }
            },
            "SUBBED": {
                "Vid Streaming": {
                    "link": "https://www051.vipanicdn.net/streamhls/74faf577636cf9b32fe7cce761e6c9c5/ep.32.1684116697.m3u8"
                },
                "Awesome Stream": {
                    "link": "https://player.ryuk.to?id=beyblade-burst-god-episode-32"
                }
            },
            "OTHER LANGUAGES": {
                "Hindi": "https://beta.awstream.net/watch?v=beyblade-burst-evolution-8211-episode-32&lang=hin"
            }
        },
        "isFiller": false,
        "downloadLink": {
            "DUBBED": "MTEzNTYw",
            "SUBBED": "MjA0NTEw"
        }
    },
    "33": {
        "intro": null,
        "title": "Episode 33",
        "source": {
            "DUBBED": {
                "Vid Streaming": {
                    "link": "https://www012.vipanicdn.net/streamhls/968970cf6ed021390570a7a4dc5c2abb/ep.33.1677678135.m3u8"
                },
                "Awesome Stream": {
                    "link": "https://player.ryuk.to?id=beyblade-burst-god-episode-dub-33"
                }
            },
            "SUBBED": {
                "Vid Streaming": {
                    "link": "https://www052.vipanicdn.net/streamhls/74faf577636cf9b32fe7cce761e6c9c5/ep.33.1684116466.m3u8"
                },
                "Awesome Stream": {
                    "link": "https://player.ryuk.to?id=beyblade-burst-god-episode-33"
                }
            },
            "OTHER LANGUAGES": {
                "Hindi": "https://beta.awstream.net/watch?v=beyblade-burst-evolution-8211-episode-33&lang=hin"
            }
        },
        "isFiller": false,
        "downloadLink": {
            "DUBBED": "MTEzNTYx",
            "SUBBED": "MjA0NTEx"
        }
    },
    "34": {
        "intro": null,
        "title": "Episode 34",
        "source": {
            "DUBBED": {
                "Vid Streaming": {
                    "link": "https://www013.vipanicdn.net/streamhls/968970cf6ed021390570a7a4dc5c2abb/ep.34.1677685093.m3u8"
                },
                "Awesome Stream": {
                    "link": "https://player.ryuk.to?id=beyblade-burst-god-episode-dub-34"
                }
            },
            "SUBBED": {
                "Vid Streaming": {
                    "link": "https://www054.vipanicdn.net/streamhls/74faf577636cf9b32fe7cce761e6c9c5/ep.34.1685516972.m3u8"
                },
                "Awesome Stream": {
                    "link": "https://player.ryuk.to?id=beyblade-burst-god-episode-34"
                }
            },
            "OTHER LANGUAGES": {
                "Hindi": "https://beta.awstream.net/watch?v=beyblade-burst-evolution-8211-episode-34&lang=hin"
            }
        },
        "isFiller": false,
        "downloadLink": {
            "DUBBED": "MTEzNTYy",
            "SUBBED": "MjA1MjE4"
        }
    },
    "35": {
        "intro": null,
        "title": "Episode 35",
        "source": {
            "DUBBED": {
                "Vid Streaming": {
                    "link": "https://www014.vipanicdn.net/streamhls/968970cf6ed021390570a7a4dc5c2abb/ep.35.1677676742.m3u8"
                },
                "Awesome Stream": {
                    "link": "https://player.ryuk.to?id=beyblade-burst-god-episode-dub-35"
                }
            },
            "SUBBED": {
                "Vid Streaming": {
                    "link": "https://www049.vipanicdn.net/streamhls/74faf577636cf9b32fe7cce761e6c9c5/ep.35.1689578063.m3u8"
                },
                "Awesome Stream": {
                    "link": "https://player.ryuk.to?id=beyblade-burst-god-episode-35"
                }
            },
            "OTHER LANGUAGES": {
                "Hindi": "https://beta.awstream.net/watch?v=beyblade-burst-evolution-8211-episode-35&lang=hin"
            }
        },
        "isFiller": false,
        "downloadLink": {
            "DUBBED": "MTEzNTYz",
            "SUBBED": "MjA3MDA4"
        }
    },
    "36": {
        "intro": null,
        "title": "Episode 36",
        "source": {
            "DUBBED": {
                "Vid Streaming": {
                    "link": "https://www015.vipanicdn.net/streamhls/968970cf6ed021390570a7a4dc5c2abb/ep.36.1677681085.m3u8"
                },
                "Awesome Stream": {
                    "link": "https://player.ryuk.to?id=beyblade-burst-god-episode-dub-36"
                }
            },
            "SUBBED": {
                "Vid Streaming": {
                    "link": "https://www049.vipanicdn.net/streamhls/74faf577636cf9b32fe7cce761e6c9c5/ep.36.1689569380.m3u8"
                },
                "Awesome Stream": {
                    "link": "https://player.ryuk.to?id=beyblade-burst-god-episode-36"
                }
            },
            "OTHER LANGUAGES": {
                "Hindi": "https://beta.awstream.net/watch?v=beyblade-burst-evolution-8211-episode-36&lang=hin"
            }
        },
        "isFiller": false,
        "downloadLink": {
            "DUBBED": "MTEzNTY0",
            "SUBBED": "MjA4MzM4"
        }
    },
    "37": {
        "intro": null,
        "title": "Episode 37",
        "source": {
            "DUBBED": {
                "Vid Streaming": {
                    "link": "https://www016.vipanicdn.net/streamhls/968970cf6ed021390570a7a4dc5c2abb/ep.37.1677686975.m3u8"
                },
                "Awesome Stream": {
                    "link": "https://player.ryuk.to?id=beyblade-burst-god-episode-dub-37"
                }
            },
            "SUBBED": {
                "Vid Streaming": {
                    "link": "https://www042.vipanicdn.net/streamhls/74faf577636cf9b32fe7cce761e6c9c5/ep.37.1690960468.m3u8"
                },
                "Awesome Stream": {
                    "link": "https://player.ryuk.to?id=beyblade-burst-god-episode-37"
                }
            },
            "OTHER LANGUAGES": {
                "Hindi": "https://beta.awstream.net/watch?v=beyblade-burst-evolution-8211-episode-37&lang=hin"
            }
        },
        "isFiller": false,
        "downloadLink": {
            "DUBBED": "MTEzNTY1",
            "SUBBED": "MjA5NDQx"
        }
    },
    "38": {
        "intro": null,
        "title": "Episode 38",
        "source": {
            "DUBBED": {
                "Vid Streaming": {
                    "link": "https://www017.vipanicdn.net/streamhls/968970cf6ed021390570a7a4dc5c2abb/ep.38.1677690069.m3u8"
                },
                "Awesome Stream": {
                    "link": "https://player.ryuk.to?id=beyblade-burst-god-episode-dub-38"
                }
            },
            "SUBBED": {
                "Vid Streaming": {
                    "link": "https://www044.vipanicdn.net/streamhls/74faf577636cf9b32fe7cce761e6c9c5/ep.38.1691126113.m3u8"
                },
                "Awesome Stream": {
                    "link": "https://player.ryuk.to?id=beyblade-burst-god-episode-38"
                }
            },
            "OTHER LANGUAGES": {
                "Hindi": "https://beta.awstream.net/watch?v=beyblade-burst-evolution-8211-episode-38&lang=hin"
            }
        },
        "isFiller": false,
        "downloadLink": {
            "DUBBED": "MTEzNTY2",
            "SUBBED": "MjA5NTIz"
        }
    },
    "39": {
        "intro": null,
        "title": "Episode 39",
        "source": {
            "DUBBED": {
                "Vid Streaming": {
                    "link": "https://www018.vipanicdn.net/streamhls/968970cf6ed021390570a7a4dc5c2abb/ep.39.1677684548.m3u8"
                },
                "Awesome Stream": {
                    "link": "https://player.ryuk.to?id=beyblade-burst-god-episode-dub-39"
                }
            },
            "SUBBED": {
                "Vid Streaming": {
                    "link": "https://www042.vipanicdn.net/streamhls/74faf577636cf9b32fe7cce761e6c9c5/ep.39.1693199840.m3u8"
                },
                "Awesome Stream": {
                    "link": "https://player.ryuk.to?id=beyblade-burst-god-episode-39"
                }
            },
            "OTHER LANGUAGES": {
                "Hindi": "https://beta.awstream.net/watch?v=beyblade-burst-evolution-8211-episode-39&lang=hin"
            }
        },
        "isFiller": false,
        "downloadLink": {
            "DUBBED": "MTEzNTY3",
            "SUBBED": "MjEwODUx"
        }
    },
    "40": {
        "intro": null,
        "title": "Episode 40",
        "source": {
            "DUBBED": {
                "Vid Streaming": {
                    "link": "https://www019.vipanicdn.net/streamhls/968970cf6ed021390570a7a4dc5c2abb/ep.40.1677687733.m3u8"
                },
                "Awesome Stream": {
                    "link": "https://player.ryuk.to?id=beyblade-burst-god-episode-dub-40"
                }
            },
            "SUBBED": {
                "Vid Streaming": {
                    "link": "https://www044.vipanicdn.net/streamhls/74faf577636cf9b32fe7cce761e6c9c5/ep.40.1693275770.m3u8"
                },
                "Awesome Stream": {
                    "link": "https://player.ryuk.to?id=beyblade-burst-god-episode-40"
                }
            },
            "OTHER LANGUAGES": {
                "Hindi": "https://beta.awstream.net/watch?v=beyblade-burst-evolution-8211-episode-40&lang=hin"
            }
        },
        "isFiller": false,
        "downloadLink": {
            "DUBBED": "MTEzNTY4",
            "SUBBED": "MjEwODgz"
        }
    },
    "41": {
        "intro": null,
        "title": "Episode 41",
        "source": {
            "DUBBED": {
                "Vid Streaming": {
                    "link": "https://www021.vipanicdn.net/streamhls/968970cf6ed021390570a7a4dc5c2abb/ep.41.1677688450.m3u8"
                },
                "Awesome Stream": {
                    "link": "https://player.ryuk.to?id=beyblade-burst-god-episode-dub-41"
                }
            },
            "SUBBED": {
                "Vid Streaming": {
                    "link": "https://www047.vipanicdn.net/streamhls/74faf577636cf9b32fe7cce761e6c9c5/ep.41.1693449809.m3u8"
                },
                "Awesome Stream": {
                    "link": "https://player.ryuk.to?id=beyblade-burst-god-episode-41"
                }
            },
            "OTHER LANGUAGES": {
                "Hindi": "https://beta.awstream.net/watch?v=beyblade-burst-evolution-8211-episode-41&lang=hin"
            }
        },
        "isFiller": false,
        "downloadLink": {
            "DUBBED": "MTE1Njcw",
            "SUBBED": "MjExMDA2"
        }
    },
    "42": {
        "intro": null,
        "title": "Episode 42",
        "source": {
            "DUBBED": {
                "Vid Streaming": {
                    "link": "https://www022.vipanicdn.net/streamhls/968970cf6ed021390570a7a4dc5c2abb/ep.42.1677683192.m3u8"
                },
                "Awesome Stream": {
                    "link": "https://player.ryuk.to?id=beyblade-burst-god-episode-dub-42"
                }
            },
            "SUBBED": {
                "Vid Streaming": {
                    "link": "https://www047.vipanicdn.net/streamhls/74faf577636cf9b32fe7cce761e6c9c5/ep.42.1696211144.m3u8"
                },
                "Awesome Stream": {
                    "link": "https://player.ryuk.to?id=beyblade-burst-god-episode-42"
                }
            },
            "OTHER LANGUAGES": {
                "Hindi": "https://beta.awstream.net/watch?v=beyblade-burst-evolution-8211-episode-42&lang=hin"
            }
        },
        "isFiller": false,
        "downloadLink": {
            "DUBBED": "MTE1Njcx",
            "SUBBED": "MjEyNjg2"
        }
    },
    "43": {
        "intro": null,
        "title": "Episode 43",
        "source": {
            "DUBBED": {
                "Vid Streaming": {
                    "link": "https://www023.vipanicdn.net/streamhls/968970cf6ed021390570a7a4dc5c2abb/ep.43.1677757414.m3u8"
                },
                "Awesome Stream": {
                    "link": "https://player.ryuk.to?id=beyblade-burst-god-episode-dub-43"
                }
            },
            "SUBBED": {
                "Vid Streaming": {
                    "link": "https://www041.vipanicdn.net/streamhls/74faf577636cf9b32fe7cce761e6c9c5/ep.43.1696443778.m3u8"
                },
                "Awesome Stream": {
                    "link": "https://player.ryuk.to?id=beyblade-burst-god-episode-43"
                }
            },
            "OTHER LANGUAGES": {
                "Hindi": "https://beta.awstream.net/watch?v=beyblade-burst-evolution-8211-episode-43&lang=hin"
            }
        },
        "isFiller": false,
        "downloadLink": {
            "DUBBED": "MTE1Njcy",
            "SUBBED": "MjEyODkw"
        }
    },
    "44": {
        "intro": null,
        "title": "Episode 44",
        "source": {
            "DUBBED": {
                "Vid Streaming": {
                    "link": "https://www024.vipanicdn.net/streamhls/968970cf6ed021390570a7a4dc5c2abb/ep.44.1677692942.m3u8"
                },
                "Awesome Stream": {
                    "link": "https://player.ryuk.to?id=beyblade-burst-god-episode-dub-44"
                }
            },
            "SUBBED": {
                "Vid Streaming": {
                    "link": "https://www049.vipanicdn.net/streamhls/74faf577636cf9b32fe7cce761e6c9c5/ep.44.1696504293.m3u8"
                },
                "Awesome Stream": {
                    "link": "https://player.ryuk.to?id=beyblade-burst-god-episode-44"
                }
            },
            "OTHER LANGUAGES": {
                "Hindi": "https://beta.awstream.net/watch?v=beyblade-burst-evolution-8211-episode-44&lang=hin"
            }
        },
        "isFiller": false,
        "downloadLink": {
            "DUBBED": "MTE1Njcz",
            "SUBBED": "MjEyOTA4"
        }
    },
    "45": {
        "intro": null,
        "title": "Episode 45",
        "source": {
            "DUBBED": {
                "Vid Streaming": {
                    "link": "https://www025.vipanicdn.net/streamhls/968970cf6ed021390570a7a4dc5c2abb/ep.45.1677778586.m3u8"
                },
                "Awesome Stream": {
                    "link": "https://player.ryuk.to?id=beyblade-burst-god-episode-dub-45"
                }
            },
            "SUBBED": {
                "Vid Streaming": {
                    "link": "https://www050.vipanicdn.net/streamhls/74faf577636cf9b32fe7cce761e6c9c5/ep.45.1696565969.m3u8"
                },
                "Awesome Stream": {
                    "link": "https://player.ryuk.to?id=beyblade-burst-god-episode-45"
                }
            },
            "OTHER LANGUAGES": {
                "Hindi": "https://beta.awstream.net/watch?v=beyblade-burst-evolution-8211-episode-45&lang=hin"
            }
        },
        "isFiller": false,
        "downloadLink": {
            "DUBBED": "MTE1Njc0",
            "SUBBED": "MjEyOTI5"
        }
    },
    "46": {
        "intro": null,
        "title": "Episode 46",
        "source": {
            "DUBBED": {
                "Vid Streaming": {
                    "link": "https://www026.vipanicdn.net/streamhls/968970cf6ed021390570a7a4dc5c2abb/ep.46.1677694282.m3u8"
                },
                "Awesome Stream": {
                    "link": "https://player.ryuk.to?id=beyblade-burst-god-episode-dub-46"
                }
            },
            "SUBBED": {
                "Vid Streaming": {
                    "link": "https://www050.vipanicdn.net/streamhls/74faf577636cf9b32fe7cce761e6c9c5/ep.46.1696907375.m3u8"
                },
                "Awesome Stream": {
                    "link": "https://player.ryuk.to?id=beyblade-burst-god-episode-46"
                }
            },
            "OTHER LANGUAGES": {
                "Hindi": "https://beta.awstream.net/watch?v=beyblade-burst-evolution-8211-episode-46&lang=hin"
            }
        },
        "isFiller": false,
        "downloadLink": {
            "DUBBED": "MTE1Njc1",
            "SUBBED": "MjEzMDc5"
        }
    },
    "47": {
        "intro": null,
        "title": "Episode 47",
        "source": {
            "DUBBED": {
                "Vid Streaming": {
                    "link": "https://www027.vipanicdn.net/streamhls/968970cf6ed021390570a7a4dc5c2abb/ep.47.1677749715.m3u8"
                },
                "Awesome Stream": {
                    "link": "https://player.ryuk.to?id=beyblade-burst-god-episode-dub-47"
                }
            },
            "SUBBED": {
                "Awesome Stream": {
                    "link": "https://player.ryuk.to?id=beyblade-burst-god-episode-47"
                }
            },
            "OTHER LANGUAGES": {
                "Hindi": "https://beta.awstream.net/watch?v=beyblade-burst-evolution-8211-episode-47&lang=hin"
            }
        },
        "isFiller": false,
        "downloadLink": {
            "DUBBED": "MTE1Njc2"
        }
    },
    "48": {
        "intro": null,
        "title": "Episode 48",
        "source": {
            "DUBBED": {
                "Vid Streaming": {
                    "link": "https://www028.vipanicdn.net/streamhls/968970cf6ed021390570a7a4dc5c2abb/ep.48.1677692004.m3u8"
                },
                "Awesome Stream": {
                    "link": "https://player.ryuk.to?id=beyblade-burst-god-episode-dub-48"
                }
            },
            "SUBBED": {
                "Awesome Stream": {
                    "link": "https://player.ryuk.to?id=beyblade-burst-god-episode-48"
                }
            },
            "OTHER LANGUAGES": {
                "Hindi": "https://beta.awstream.net/watch?v=beyblade-burst-evolution-8211-episode-48&lang=hin"
            }
        },
        "isFiller": false,
        "downloadLink": {
            "DUBBED": "MTE1Njc3"
        }
    },
    "49": {
        "intro": null,
        "title": "Episode 49",
        "source": {
            "DUBBED": {
                "Vid Streaming": {
                    "link": "https://www029.vipanicdn.net/streamhls/968970cf6ed021390570a7a4dc5c2abb/ep.49.1677690553.m3u8"
                },
                "Awesome Stream": {
                    "link": "https://player.ryuk.to?id=beyblade-burst-god-episode-dub-49"
                }
            },
            "SUBBED": {
                "Awesome Stream": {
                    "link": "https://player.ryuk.to?id=beyblade-burst-god-episode-49"
                }
            },
            "OTHER LANGUAGES": {
                "Hindi": "https://beta.awstream.net/watch?v=beyblade-burst-evolution-8211-episode-49&lang=hin"
            }
        },
        "isFiller": false,
        "downloadLink": {
            "DUBBED": "MTE1Njc4"
        }
    },
    "50": {
        "intro": null,
        "title": "Episode 50",
        "source": {
            "DUBBED": {
                "Vid Streaming": {
                    "link": "https://www030.vipanicdn.net/streamhls/968970cf6ed021390570a7a4dc5c2abb/ep.50.1677688050.m3u8"
                },
                "Awesome Stream": {
                    "link": "https://player.ryuk.to?id=beyblade-burst-god-episode-dub-50"
                }
            },
            "SUBBED": {
                "Awesome Stream": {
                    "link": "https://player.ryuk.to?id=beyblade-burst-god-episode-50"
                }
            },
            "OTHER LANGUAGES": {
                "Hindi": "https://beta.awstream.net/watch?v=beyblade-burst-evolution-8211-episode-50&lang=hin"
            }
        },
        "isFiller": false,
        "downloadLink": {
            "DUBBED": "MTE1Njc5"
        }
    },
    "51": {
        "intro": null,
        "title": "Episode 51",
        "source": {
            "DUBBED": {
                "Vid Streaming": {
                    "link": "https://www001.vipanicdn.net/streamhls/968970cf6ed021390570a7a4dc5c2abb/ep.51.1677692053.m3u8"
                },
                "Awesome Stream": {
                    "link": "https://player.ryuk.to?id=beyblade-burst-god-episode-dub-51"
                }
            },
            "SUBBED": {
                "Awesome Stream": {
                    "link": "https://player.ryuk.to?id=beyblade-burst-god-episode-51"
                }
            },
            "OTHER LANGUAGES": {
                "Hindi": "https://beta.awstream.net/watch?v=beyblade-burst-evolution-8211-episode-51&lang=hin"
            }
        },
        "isFiller": false,
        "downloadLink": {
            "DUBBED": "MTE1Njgw"
        }
    }
}