{
    "jap": {
        "no_epi": "12",
        "link": "https://player.ryuk.to?id=tian-mei-de-yao-hen-episode-",
        "down_links": [
            "MTkxNjU0",
            "MTkxNjY0",
            "MTkxNjc1",
            "MTkxODQ1",
            "MTkyMjk2",
            "MTkzMDE3",
            "MTkzMDQ0",
            "MTkzNTMy",
            "MTkzNjU3",
            "MTkzOTcy",
            "MTk0NTY3",
            "MTk0NTY4"
        ]
    },
    "eng": {
        "no_epi": 0,
        "link": "https://player.ryuk.to?id=tian-mei-de-yao-hen-dub-episode-",
        "down_links": []
    },
    "episodes_names": [
        "01 "
    ]
}