{
    "jap": {
        "no_epi": "24",
        "link": "https://player.ryuk.to?id=accel-world-episode-",
        "down_links": [
            "NDIwMg",
            "NDI4NA",
            "NDI4MA",
            "NDI3OA",
            "NDI3NA",
            "NDI3MQ",
            "NDI2OQ",
            "NDI2OA",
            "NDI2Mg",
            "NDI2MA",
            "NDI1Nw",
            "NDI1Mw",
            "NDIzOA",
            "NDIzNA",
            "NDIyOQ",
            "NDIyNw",
            "NDIyNQ",
            "NDIyMg",
            "NDIyMQ",
            "NDIxNQ",
            "NDIxNA",
            "NDIxMg",
            "NDIwOQ",
            "NDIwNg"
        ]
    },
    "eng": {
        "no_epi": "24",
        "link": "https://player.ryuk.to?id=accel-world-dub-episode-",
        "down_links": [
            "NzQxMzk",
            "NzQxNDA",
            "NzQxNDE",
            "NzQxNDI",
            "MTE2OTI3",
            "NzQxNDM",
            "NzQxNDQ",
            "NzQxNDU",
            "NzQxNDY",
            "NzQxNDc",
            "NzQxNDg",
            "NzQxNDk",
            "NzQxNTA",
            "NzQxNTE",
            "NzQxNTI",
            "NzQxNTM",
            "NzQxNTQ",
            "NzQxNTU",
            "NzQxNTY",
            "NzQxNTc",
            "NzQxNTg",
            "NzQxNTk",
            "NzQxNjA",
            "NzQxNjE"
        ]
    },
    "episodes_names": [
        "Episode 1 - Acceleration",
        "Episode 2 - Transformation",
        "Episode 3 - Investigation",
        "Episode 4 - Declaration",
        "Episode 5 - Aviation",
        "Episode 6 - Retribution",
        "Episode 7 - Restoration",
        "Episode 8 - Temptation",
        "Episode 9 - Escalation",
        "Episode 10 - Activation",
        "Episode 11 - Obligation",
        "Episode 12 - Absolution",
        "Episode 13 - Violation",
        "Episode 14 - Arrestation",
        "Episode 15 - Destruction",
        "Episode 16 - Imagination",
        "Episode 17 - Fragmentation",
        "Episode 18 - Invitation",
        "Episode 19 - Revolution",
        "Episode 20 - Domination",
        "Episode 21 - Insurrection",
        "Episode 22 - Determination",
        "Episode 23 - Consolidation",
        "Episode 24 - Reincarnation"
    ]
}