{
    "jap": {
        "no_epi": "64",
        "link": "https://player.ryuk.to?id=doupo-cangqiong-nian-fan-episode-",
        "down_links": [
            "MTg5OTA5",
            "MTg5OTEx",
            "MTg5OTI0",
            "MTkwMjI3",
            "MTkwNTEz",
            "MTkwNzkw",
            "MTkxMjE2",
            "MTkxNTkx",
            "MTkyMDEz",
            "MTkyNDEx",
            "MTkyNzgw",
            "MTkzMTkw",
            "MTkzNTAy",
            "MTkzNzcx",
            "MTk0MDU2",
            "MTk0MzY5",
            "MTk0Njkz",
            "MTk0OTU1",
            "MTk1MjEy",
            "MTk1NDgw",
            "MTk1Nzk1",
            "MTk2MDYw",
            "MTk2NDAx",
            "MTk2Nzg3",
            "MTk3MDU2",
            "MTk3Mzk0",
            "MTk3Njcw",
            "MTk3OTYx",
            "MTk4Mjc4",
            "MTk4NjYz",
            "MTk5MDQ0",
            "MTk5NTMx",
            "MTk5ODU0",
            "MjAwMjE1",
            "MjAwODI2",
            "MjAxMjcx",
            "MjAxNjYx",
            "MjAyMDUz",
            "MjAyNDY1",
            "MjAyOTQw",
            "MjAzMjgz",
            "MjAzNjk0",
            "MjA0MDgx",
            "MjA0NDk3",
            "MjA0NzU3",
            "MjA1MDgy",
            "MjA1NTE0",
            "MjA2MDAy",
            "MjA2NDMx",
            "MjA2ODc3",
            "MjA3Mzgx",
            "MjA3ODY4",
            "MjA4MzAy",
            "MjA4Njgz",
            "MjA5MTk0",
            "MjA5NjQw"
        ]
    },
    "eng": {
        "no_epi": "52",
        "link": "https://player.ryuk.to?id=doupo-cangqiong-nian-fan-dub-episode-",
        "down_links": [
            "",
            "",
            "",
            "",
            "",
            "",
            "",
            "",
            "",
            "",
            "",
            "",
            "",
            "",
            "",
            "",
            "",
            "",
            "",
            "",
            "",
            "",
            "",
            "",
            "",
            "",
            "",
            "",
            "",
            "",
            "",
            "",
            "",
            "",
            "",
            "",
            "",
            "",
            "",
            "",
            "",
            "",
            "",
            "",
            "",
            "",
            "",
            "",
            "",
            "",
            "",
            ""
        ]
    },
    "episodes_names": [
        "Battle Through The Heavens 5th Season"
    ]
}