{
    "jap": {
        "no_epi": "26",
        "link": "https://player.ryuk.to?id=shin-atashin-chi-episode-",
        "down_links": [
            "NjkxMDk",
            "NjkyMTM",
            "NjkyMTQ",
            "NjkyMTU",
            "Njk0NzQ",
            "Njk1NjM",
            "Njk2NDA",
            "Njk3MjA",
            "Njk4MDg",
            "NzAwMTQ",
            "NzAwOTE",
            "NzAxNzI",
            "NzAzMjg",
            "NzAzMjk",
            "NzA0MTc",
            "NzA0OTI",
            "NzA1Njg",
            "NzA2NDU",
            "NzA3Mjk",
            "NzA4MjA",
            "NzA5MTA",
            "NzEwMjk",
            "NzExMDM",
            "NzEyNTY",
            "NzEzMTU",
            "NzEzMTY"
        ]
    },
    "eng": {
        "no_epi": 0,
        "link": "https://player.ryuk.to?id=shin-atashin-chi-dub-episode-",
        "down_links": []
    },
    "episodes_names": [
        "Episode 1 - Strong-Willed Mom! | Yuzu Wants to Wear Sunglasses | Mom Likes New Weapons",
        "Episode 2 - Mikan is Reset to Factory Settings | We've Been Here For a While | Dad is Very Tolerant",
        "Episode 3 - Yuzupi's Mother | Mothers' Bowling | Beware Mom's Angry Glare",
        "Episode 4 - Kawashima's Charm | Mizushima-san is Young | Take Care of Your Own Butt!",
        "Episode 5 - Mom's on the Ball | Yuzu and Friends Go to the Movies | Men's Peace",
        "Episode 6 - Mom and the Jigsaw Puzzle | Mikan Confuses | Simple Meals",
        "Episode 7 - Shiny Forehead | Mom, the Refill Genius | Man\u2019s Bluntness",
        "Episode 8 - Pull Out That Gray Hair | Yuzu Is Bad At Not Being Independent | What Does Dad See in Mom?",
        "Episode 9 - Mom, in the Hip Bath | Yoshioka Envy! | Mom's Rejuvenation Methods",
        "Episode 10 - Sudou-chan's Glasses | Donut Fever | What I'm Into Lately",
        "Episode 11 - Mikan, the Window-cleaning Pro | Mom's Hunch Intelligence | Mom's Not Good at Examples",
        "Episode 12 - A Beary Christmas | Prehistoric Mom Swears on Her Intuition | Iwaki-kun and the Christmas Cake",
        "Episode 13 - New Year's at the Tachibana House | The Mochi Competition | New Year's is Too Short",
        "Episode 14 - Dad Doesn't Consult | Mom's Brain Training | Ugh, Boys",
        "Episode 15 - Mom Spaces Out | Nasuo's Character Bentos | Is This No-Creepo?",
        "Episode 16 - Mom Is Strangely Intuitive | According to Men's Plan | You-Can-Do-It Beam",
        "Episode 17 - Takkun's Bean Throwing Festival | Mikan's a Boor | The Guineafowl Incident",
        "Episode 18 - Mothers, Parents to the Entrance Exam Students | Mikan's Valentine | Yuzu's Late-night Men's Meal",
        "Episode 19 - Mikan Doesn't Want to Help | Nothing Beats Dad's Kindness | I Want Hamburg Steaks",
        "Episode 20 - Takkun the Big Eater | Mom, Dad, Trekking | Mikan Drops the Balls",
        "Episode 21 - The Smart Way of Returning an Umbrella | Why Did You Just Laugh? | Yuzu and the Shadow Realm",
        "Episode 22 - Mom Understands Dad | Rabbit Doodles | Yoshioka Doesn't Want to Take an Umbrella",
        "Episode 23 - They'll Never Notice | Mom Pretends She Knows | The Yuzu-Fandom's Hallowed Ground",
        "Episode 24 - Mom's Surprise Present | Yuzuhiko and the Baseball Club (Part One) | Yuzuhiko and the Baseball Club (Part Two)",
        "Episode 25 - The Hot Spring Slippers | Yoshioka Hates Fish | Yuzu's Nicknames",
        "Episode 26 - This House is My Castle! | Mikan and the Cherry Blossom Viewing | Everybody's Dream"
    ]
}