{
    "jap": {
        "no_epi": "13",
        "link": "https://player.ryuk.to?id=kanamemo-episode-",
        "down_links": [
            "MjU5MTA=",
            "MjU5MTE=",
            "MjU5MTM=",
            "MjU5MTQ=",
            "MjU5MTY=",
            "MjU5MTc=",
            "MjU5MTg=",
            "MjU5MTk=",
            "MjU5MjA=",
            "MjU5MjE=",
            "MjU5MjI=",
            "MjU5MjM=",
            "MjU5MjQ="
        ]
    },
    "episodes_names": [
        "Solitude, For the First Time",
        "My First Paper Delivery",
        "The First Smile",
        "My First Time at the Pool",
        "My First Time at the Bath with Everyone",
        "My First Scary Story",
        "My First Welcome",
        "My First Talk About Memories",
        "My First Diet?",
        "My First Feelings",
        "My First Time Nursing",
        "The First Person",
        "And the first..."
    ],
    "fillers": []
}