{
    "jap": {
        "no_epi": "1",
        "link": "https://player.ryuk.to?id=boruto-naruto-the-movie-naruto-ga-hokage-ni-natta-hi-episode-",
        "down_links": [
            "NzI5NzE"
        ]
    },
    "eng": {
        "no_epi": 0,
        "link": "https://player.ryuk.to?id=boruto-naruto-the-movie-naruto-ga-hokage-ni-natta-hi-dub-episode-",
        "down_links": []
    },
    "episodes_names": [
        "Boruto: Naruto the Movie - The Day Naruto Became the Hokage",
        "Boruto: Naruto the Movie - The Day Naruto Became the Hokage"
    ]
}