{
    "jap": {
        "no_epi": "12",
        "link": "https://player.ryuk.to?id=boku-dake-ga-inai-machi-episode-",
        "down_links": [
            "NzAyNzk",
            "NzAzNTE",
            "NzA0MzI",
            "NzA1MDk",
            "NzA1ODQ",
            "NzA2NTk",
            "NzA3NDE",
            "NzA4MzM",
            "NzA5MjY",
            "NzEwNDI",
            "NzExMTc",
            "NzExOTI"
        ]
    },
    "eng": {
        "no_epi": "12",
        "link": "https://player.ryuk.to?id=boku-dake-ga-inai-machi-dub-episode-",
        "down_links": [
            "MTE4MzY3",
            "MTE4MzY4",
            "MTE4MzY5",
            "MTE4Mzcw",
            "MTE4Mzcx",
            "MTE4Mzcy",
            "MTE4Mzcz",
            "MTE4Mzc0",
            "MTE4Mzc1",
            "MTE4Mzc2",
            "MTE4Mzc3",
            "MTE4Mzc4"
        ]
    },
    "episodes_names": [
        "Episode 1 - Flashing Before My Eyes",
        "Episode 2 - Palm of the Hand",
        "Episode 3 - Birthmark",
        "Episode 4 - Accomplishment",
        "Episode 5 - Getaway",
        "Episode 6 - Grim Reaper",
        "Episode 7 - Out of Control",
        "Episode 8 - Spiral",
        "Episode 9 - Closure",
        "Episode 10 - Joy",
        "Episode 11 - Future",
        "Episode 12 - Treasure"
    ]
}